clc/__init__.py
clc/__main__.py
clc/clc.py
codelinescounter-0.0.3.dist-info/LICENSE
codelinescounter-0.0.3.dist-info/METADATA
codelinescounter-0.0.3.dist-info/WHEEL
codelinescounter-0.0.3.dist-info/top_level.txt
codelinescounter-0.0.3.dist-info/RECORD
