Metadata-Version: 2.1
Name: codelinescounter
Version: 0.0.3
Summary: Python library for counting lines of python code in file or directory
Home-page: https://github.com/AndK17/codelinescounter
Author: AndK
Author-email: karpukhin_av@mail.ru
License: GNU GPL v3
Keywords: count code,count lines,code lines,lines
Platform: UNKNOWN
License-File: LICENSE
Requires-Dist: prettytable
